lpde/__init__.py
lpde/dataset.py
lpde/model.py
lpde/network.py
lpde/utils.py
lpde-0.1.1.dist-info/LICENSE
lpde-0.1.1.dist-info/METADATA
lpde-0.1.1.dist-info/WHEEL
lpde-0.1.1.dist-info/top_level.txt
lpde-0.1.1.dist-info/RECORD
