Metadata-Version: 2.1
Name: lpde
Version: 0.1.1
Summary: Learning Partial Differential Equations
Home-page: http://github.com/fkemeth/lpde
Author: Felix P. Kemeth
Author-email: felix@kemeth.de
License: MIT
Project-URL: Bug Tracker, https://github.com/fkemeth/lpde/issues
Classifier: License :: OSI Approved :: MIT License
Classifier: Operating System :: OS Independent
Classifier: Programming Language :: Python :: 3
Classifier: Programming Language :: Python :: 3 :: Only
Classifier: Programming Language :: Python :: 3.7
Classifier: Programming Language :: Python :: 3.8
Classifier: Programming Language :: Python :: 3.9
Classifier: Programming Language :: Python :: 3.10
Requires-Python: >=3.7
License-File: LICENSE
Requires-Dist: findiff
Requires-Dist: scipy
Requires-Dist: scikit-learn
Requires-Dist: torch
Requires-Dist: tqdm
